src/normal.sv
// ============================================================================
//  normal.sv
//  ----------------------------------------------------------------------------
//  Heightmap normal stage.
//
//  Consumes the compact marcher->normal contract for one pixel/ray:
//      - status
//      - hit cell indices (ix, iy)
//      - hit height (h_hit)
//      - pixel coordinates (px, py)
//      - valid
//
//  Then issues 4 neighbouring heightmap reads:
//      (ix-1, iy), (ix+1, iy), (ix, iy-1), (ix, iy+1)
//
//  and computes a gradient-based surface normal:
//      Nx ~ -(h[x+1,y] - h[x-1,y])
//      Ny ~ -(h[x,y+1] - h[x,y-1])
//      Nz = +1.0
//
//  Notes:
//      - One module instance handles a stream of pixels/rays over time,
//        not one whole frame at once.
//      - This module outputs an un-normalized normal in DIR-format.
//        The shader stage can use it directly for approximate lighting.
//      - At the output of the fixed-depth marcher, status=2'b00 means
//        "no hit found within N_STEPS" (MISS), even though the internal
//        marcher code names 2'b00 as ST_MARCHING.
//
//  Interface summary:
//      Inputs from marcher:
//          status_in, ix_in, iy_in, h_hit_in, step_count_in,
//          px_in, py_in, valid_in
//      Outputs to shader:
//          status_out, ix_out, iy_out, h_hit_out, step_count_out,
//          Nx_out, Ny_out, Nz_out,
//          px_out, py_out, valid_out
//
//  Pipeline:
//      Stage 1: latch marcher result, compute clamped neighbour indices
//      Stage 2: BRAM read latency (4 reads return)
//      Stage 3: compute normal, forward to shader
//
//  Total latency: 3 cycles
// ============================================================================

module normal #(
    // ----- Heightmap geometry -----
    parameter int GRID_N     = 256,
    parameter int IDX_W      = $clog2(GRID_N),

    // ----- Heightmap value format -----
    parameter int H_W        = 16,
    parameter int H_I        = 4,
    parameter int H_F        = H_W - 1 - H_I,

    // ----- Fixed-point output format for normal components -----
    // Direction components D and basis vectors: signed Q(I_D).(F_D)
    parameter int DIR_W      = 16,
    parameter int DIR_I      = 2,
    parameter int DIR_F      = DIR_W - 1 - DIR_I,

    // ----- Pixel coordinate widths -----
    parameter int PX_W       = 10,
    parameter int PY_W       = 10,

    // ----- Hit-distance proxy width -----
    parameter int STEP_W     = 5
)(
    input  logic                       clk,
    input  logic                       rst_n,
    input  logic                       en,           // pipeline enable (~stall)

    // ----- From marcher -----
    input  logic [1:0]                 status_in,    // 01=HIT, 10=OFF_GRID, 00=MISS
    input  logic [IDX_W-1:0]           ix_in,
    input  logic [IDX_W-1:0]           iy_in,
    input  logic signed [H_W-1:0]      h_hit_in,
    input  logic [STEP_W-1:0]          step_count_in,
    input  logic [PX_W-1:0]            px_in,
    input  logic [PY_W-1:0]            py_in,
    input  logic                       valid_in,

    // ----- Heightmap BRAM neighbour reads -----
    // Port order:
    //   [0] = (ix-1, iy)
    //   [1] = (ix+1, iy)
    //   [2] = (ix, iy-1)
    //   [3] = (ix, iy+1)
    output logic [IDX_W*2-1:0]         bram_addr [4],
    output logic                       bram_re   [4],
    input  logic signed [H_W-1:0]      bram_dout [4],

    // ----- To shader -----
    output logic [1:0]                 status_out,
    output logic [IDX_W-1:0]           ix_out,
    output logic [IDX_W-1:0]           iy_out,
    output logic signed [H_W-1:0]      h_hit_out,
    output logic [STEP_W-1:0]          step_count_out,
    output logic signed [DIR_W-1:0]    Nx_out,
    output logic signed [DIR_W-1:0]    Ny_out,
    output logic signed [DIR_W-1:0]    Nz_out,
    output logic [PX_W-1:0]            px_out,
    output logic [PY_W-1:0]            py_out,
    output logic                       valid_out
);

    localparam logic [1:0] ST_HIT      = 2'b01;

    localparam logic signed [DIR_W-1:0] NZ_CONST = (1 <<< DIR_F);

    function automatic logic [IDX_W-1:0] clamp_dec (
        input logic [IDX_W-1:0] v
    );
        if (v == '0)
            return '0;
        else
            return v - 1'b1;
    endfunction

    function automatic logic [IDX_W-1:0] clamp_inc (
        input logic [IDX_W-1:0] v
    );
        if (v == GRID_N-1)
            return v;
        else
            return v + 1'b1;
    endfunction

    function automatic logic signed [DIR_W-1:0] hdiff_to_dir (
        input logic signed [H_W:0] hdiff
    );
        logic signed [DIR_W+H_W:0] tmp;
        begin
            tmp = hdiff;
            if (DIR_F >= H_F)
                tmp = tmp <<< (DIR_F - H_F);
            else
                tmp = tmp >>> (H_F - DIR_F);
            return tmp[DIR_W-1:0];
        end
    endfunction

    // =================================================================
    //  STAGE 1 -- latch marcher metadata and compute neighbour addresses
    // =================================================================
    logic [1:0]                 stat_s1;
    logic [IDX_W-1:0]           ix_s1, iy_s1;
    logic signed [H_W-1:0]      hhit_s1;
    logic [STEP_W-1:0]          step_s1;
    logic [PX_W-1:0]            px_s1;
    logic [PY_W-1:0]            py_s1;
    logic                       v_s1;

    logic [IDX_W-1:0]           ix_m1_s1, ix_p1_s1;
    logic [IDX_W-1:0]           iy_m1_s1, iy_p1_s1;

    always_ff @(posedge clk) begin
        if (!rst_n) begin
            v_s1 <= 1'b0;
        end else if (en) begin
            stat_s1  <= status_in;
            ix_s1    <= ix_in;
            iy_s1    <= iy_in;
            hhit_s1  <= h_hit_in;
            step_s1  <= step_count_in;
            px_s1    <= px_in;
            py_s1    <= py_in;
            v_s1     <= valid_in;

            ix_m1_s1 <= clamp_dec(ix_in);
            ix_p1_s1 <= clamp_inc(ix_in);
            iy_m1_s1 <= clamp_dec(iy_in);
            iy_p1_s1 <= clamp_inc(iy_in);
        end
    end

    assign bram_addr[0] = {iy_s1,    ix_m1_s1};
    assign bram_addr[1] = {iy_s1,    ix_p1_s1};
    assign bram_addr[2] = {iy_m1_s1, ix_s1   };
    assign bram_addr[3] = {iy_p1_s1, ix_s1   };

    // Keep the read pattern simple: always read when the pipeline slot is valid.
    assign bram_re[0] = v_s1;
    assign bram_re[1] = v_s1;
    assign bram_re[2] = v_s1;
    assign bram_re[3] = v_s1;

    // =================================================================
    //  STAGE 2 -- capture the 4 neighbouring heights from BRAM
    // =================================================================
    logic [1:0]                 stat_s2;
    logic [IDX_W-1:0]           ix_s2, iy_s2;
    logic signed [H_W-1:0]      hhit_s2;
    logic [STEP_W-1:0]          step_s2;
    logic [PX_W-1:0]            px_s2;
    logic [PY_W-1:0]            py_s2;
    logic                       v_s2;

    logic signed [H_W-1:0]      h_xm_s2, h_xp_s2;
    logic signed [H_W-1:0]      h_ym_s2, h_yp_s2;

    always_ff @(posedge clk) begin
        if (!rst_n) begin
            v_s2 <= 1'b0;
        end else if (en) begin
            stat_s2 <= stat_s1;
            ix_s2   <= ix_s1;
            iy_s2   <= iy_s1;
            hhit_s2 <= hhit_s1;
            step_s2 <= step_s1;
            px_s2   <= px_s1;
            py_s2   <= py_s1;
            v_s2    <= v_s1;

            h_xm_s2 <= bram_dout[0];
            h_xp_s2 <= bram_dout[1];
            h_ym_s2 <= bram_dout[2];
            h_yp_s2 <= bram_dout[3];
        end
    end

    // =================================================================
    //  STAGE 3 -- central-difference gradient -> normal
    // =================================================================
    logic signed [H_W:0] dx_h_s3;
    logic signed [H_W:0] dy_h_s3;
    logic signed [DIR_W-1:0] nx_s3, ny_s3;

    always_comb begin
        dx_h_s3 = $signed(h_xp_s2) - $signed(h_xm_s2);
        dy_h_s3 = $signed(h_yp_s2) - $signed(h_ym_s2);

        nx_s3 = -hdiff_to_dir(dx_h_s3);
        ny_s3 = -hdiff_to_dir(dy_h_s3);
    end

    always_ff @(posedge clk) begin
        if (!rst_n) begin
            valid_out <= 1'b0;
        end else if (en) begin
            status_out <= stat_s2;
            ix_out     <= ix_s2;
            iy_out     <= iy_s2;
            h_hit_out  <= hhit_s2;
            step_count_out <= step_s2;
            px_out     <= px_s2;
            py_out     <= py_s2;
            valid_out  <= v_s2;

            if (stat_s2 == ST_HIT) begin
                Nx_out <= nx_s3;
                Ny_out <= ny_s3;
                Nz_out <= NZ_CONST;
            end else begin
                Nx_out <= '0;
                Ny_out <= '0;
                Nz_out <= NZ_CONST;
            end
        end
    end

endmodule

src/tb/tb_normal.sv
// ============================================================================
//  tb_normal.sv
//  ----------------------------------------------------------------------------
//  Sequential testbench for normal.sv.
//
//  Drives one record at a time, waits for valid_out, compares:
//      - Nx_out, Ny_out, Nz_out  (allow +/-1 LSB)
//      - status_out, ix_out, iy_out, h_hit_out, step_count_out, px_out, py_out
//        (must pass through unchanged from inputs)
//
//  4-port fake BRAM, each port reads from the shared heightmap.hex.
//
//  Run:
//      iverilog -g2012 -o tb_normal.vvp tb_normal.sv ../normal.sv
//      vvp tb_normal.vvp
// ============================================================================
`timescale 1ns/1ps

module tb_normal;

    localparam int GRID_N  = 256;
    localparam int IDX_W   = 8;
    localparam int H_W     = 16;
    localparam int H_I     = 4;
    localparam int H_F     = H_W - 1 - H_I;
    localparam int DIR_W   = 16;
    localparam int DIR_I   = 2;
    localparam int DIR_F   = DIR_W - 1 - DIR_I;
    localparam int STEP_W  = 5;
    localparam int PX_W    = 10;
    localparam int PY_W    = 10;

    localparam int LATENCY = 3;
    localparam int TOLER   = 1;

    localparam int VPR     = 12;
    localparam int MAX_REC = 1505;
    localparam int MEM_SZ  = MAX_REC * VPR;

    logic clk = 0;
    logic rst_n = 0;
    always #5 clk = ~clk;

    // DUT I/O
    logic                       en;
    logic [1:0]                 status_in;
    logic [IDX_W-1:0]           ix_in, iy_in;
    logic signed [H_W-1:0]      h_hit_in;
    logic [STEP_W-1:0]          step_count_in;
    logic [PX_W-1:0]            px_in;
    logic [PY_W-1:0]            py_in;
    logic                       valid_in;

    logic [IDX_W*2-1:0]         bram_addr [4];
    logic                       bram_re   [4];
    logic signed [H_W-1:0]      bram_dout [4];

    logic [1:0]                 status_out;
    logic [IDX_W-1:0]           ix_out, iy_out;
    logic signed [H_W-1:0]      h_hit_out;
    logic [STEP_W-1:0]          step_count_out;
    logic signed [DIR_W-1:0]    Nx_out, Ny_out, Nz_out;
    logic [PX_W-1:0]            px_out;
    logic [PY_W-1:0]            py_out;
    logic                       valid_out;

    normal dut (.*);

    // Fake 4-port BRAM with intermediate wires (iverilog-friendly)
    logic signed [H_W-1:0] heightmap [0:GRID_N*GRID_N-1];

    genvar gi;
    generate
        for (gi = 0; gi < 4; gi++) begin : g_bram
            wire [IDX_W*2-1:0]  this_addr = bram_addr[gi];
            wire                this_re   = bram_re[gi];
            logic signed [H_W-1:0] this_dout;
            always_ff @(posedge clk) begin
                if (this_re)
                    this_dout <= heightmap[this_addr];
            end
            assign bram_dout[gi] = this_dout;
        end
    endgenerate

    // Vector memory
    logic [15:0] vectors [0:MEM_SZ-1];

    int n_tests, n_pass, n_fail;

    function automatic int abs_diff_signed(input logic signed [DIR_W-1:0] a,
                                            input logic signed [DIR_W-1:0] b);
        int d;
        d = int'(a) - int'(b);
        return (d < 0) ? -d : d;
    endfunction

    task automatic run_one(input int rec_i);
        int base;
        int waited;
        logic [1:0]              in_status;
        logic [IDX_W-1:0]        in_ix, in_iy;
        logic signed [H_W-1:0]   in_h_hit;
        logic [STEP_W-1:0]       in_step;
        logic [PX_W-1:0]         in_px;
        logic [PY_W-1:0]         in_py;
        logic signed [DIR_W-1:0] e_Nx, e_Ny, e_Nz;
        bit ok;

        base = rec_i * VPR;

        @(negedge clk);
        in_status = vectors[base + 0][1:0];
        in_ix     = vectors[base + 1][IDX_W-1:0];
        in_iy     = vectors[base + 2][IDX_W-1:0];
        in_h_hit  = vectors[base + 3];
        in_step   = vectors[base + 4][STEP_W-1:0];
        in_px     = vectors[base + 5][PX_W-1:0];
        in_py     = vectors[base + 6][PY_W-1:0];
        e_Nx      = vectors[base + 7];
        e_Ny      = vectors[base + 8];
        e_Nz      = vectors[base + 9];

        status_in     = in_status;
        ix_in         = in_ix;
        iy_in         = in_iy;
        h_hit_in      = in_h_hit;
        step_count_in = in_step;
        px_in         = in_px;
        py_in         = in_py;
        valid_in      = 1;

        @(negedge clk);
        valid_in = 0;

        waited = 0;
        while (!valid_out && waited < 2*LATENCY + 5) begin
            @(posedge clk);
            waited++;
        end

        if (!valid_out) begin
            $display("rec %0d: TIMEOUT waiting for valid_out", rec_i);
            n_fail++;
        end else begin
            n_tests++;
            ok = 1;
            if (abs_diff_signed(Nx_out, e_Nx) > TOLER) ok = 0;
            if (abs_diff_signed(Ny_out, e_Ny) > TOLER) ok = 0;
            if (abs_diff_signed(Nz_out, e_Nz) > TOLER) ok = 0;
            if (status_out     !== in_status) ok = 0;
            if (ix_out         !== in_ix)     ok = 0;
            if (iy_out         !== in_iy)     ok = 0;
            if (h_hit_out      !== in_h_hit)  ok = 0;
            if (step_count_out !== in_step)   ok = 0;
            if (px_out         !== in_px)     ok = 0;
            if (py_out         !== in_py)     ok = 0;

            if (ok) n_pass++;
            else begin
                n_fail++;
                if (n_fail <= 10) begin
                    $display("rec %0d FAIL:", rec_i);
                    $display("  in:  stat=%0d ix=%0d iy=%0d h=%0d step=%0d px=%0d py=%0d",
                             in_status, in_ix, in_iy, $signed(in_h_hit), in_step, in_px, in_py);
                    $display("  got: N=(%0d,%0d,%0d) stat=%0d ix=%0d iy=%0d h=%0d step=%0d px=%0d py=%0d",
                             $signed(Nx_out), $signed(Ny_out), $signed(Nz_out),
                             status_out, ix_out, iy_out, $signed(h_hit_out),
                             step_count_out, px_out, py_out);
                    $display("  exp: N=(%0d,%0d,%0d)",
                             $signed(e_Nx), $signed(e_Ny), $signed(e_Nz));
                end
            end
        end

        repeat (LATENCY + 2) @(posedge clk);
    endtask

    initial begin
        int rec_i;
        $dumpfile("tb_normal.vcd");
        $dumpvars(0, tb_normal);

        en = 1;
        status_in = 0; ix_in = 0; iy_in = 0; h_hit_in = 0;
        step_count_in = 0; px_in = 0; py_in = 0; valid_in = 0;
        n_tests = 0; n_pass = 0; n_fail = 0;

        $readmemh("heightmap.hex",     heightmap);
        $readmemh("normal_vectors.hex", vectors);

        rst_n = 0;
        repeat (5) @(posedge clk);
        rst_n = 1;
        repeat (2) @(posedge clk);

        rec_i = 0;
        while (rec_i < MAX_REC && (^vectors[rec_i*VPR] !== 1'bx)) begin
            run_one(rec_i);
            rec_i++;
        end

        $display("================================================");
        $display("normal TB: tested=%0d  pass=%0d  fail=%0d",
                 n_tests, n_pass, n_fail);
        if (n_fail == 0 && n_tests > 0)
            $display("RESULT: PASS");
        else
            $display("RESULT: FAIL");
        $display("================================================");
        $finish;
    end

    initial begin
        #200_000_000;
        $display("WATCHDOG TIMEOUT");
        $finish;
    end

endmodule

src/tb/tb_normal.vcd
$date
	Sun May 24 11:46:58 2026
$end
$version
	Icarus Verilog
$end
$timescale
	1ps
$end
$scope module tb_normal $end
$var wire 1 ! valid_out $end
$var wire 5 " step_count_out [4:0] $end
$var wire 2 # status_out [1:0] $end
$var wire 10 $ py_out [9:0] $end
$var wire 10 % px_out [9:0] $end
$var wire 8 & iy_out [7:0] $end
$var wire 8 ' ix_out [7:0] $end
$var wire 16 ( h_hit_out [15:0] $end
$var wire 16 ) Nz_out [15:0] $end
$var wire 16 * Ny_out [15:0] $end
$var wire 16 + Nx_out [15:0] $end
$var parameter 32 , DIR_F $end
$var parameter 32 - DIR_I $end
$var parameter 32 . DIR_W $end
$var parameter 32 / GRID_N $end
$var parameter 32 0 H_F $end
$var parameter 32 1 H_I $end
$var parameter 32 2 H_W $end
$var parameter 32 3 IDX_W $end
$var parameter 32 4 LATENCY $end
$var parameter 32 5 MAX_REC $end
$var parameter 32 6 MEM_SZ $end
$var parameter 32 7 PX_W $end
$var parameter 32 8 PY_W $end
$var parameter 32 9 STEP_W $end
$var parameter 32 : TOLER $end
$var parameter 32 ; VPR $end
$var reg 1 < clk $end
$var reg 1 = en $end
$var reg 16 > h_hit_in [15:0] $end
$var reg 8 ? ix_in [7:0] $end
$var reg 8 @ iy_in [7:0] $end
$var reg 10 A px_in [9:0] $end
$var reg 10 B py_in [9:0] $end
$var reg 1 C rst_n $end
$var reg 2 D status_in [1:0] $end
$var reg 5 E step_count_in [4:0] $end
$var reg 1 F valid_in $end
$var integer 32 G n_fail [31:0] $end
$var integer 32 H n_pass [31:0] $end
$var integer 32 I n_tests [31:0] $end
$scope function abs_diff_signed $end
$upscope $end
$scope begin g_bram[0] $end
$var wire 16 J this_addr [15:0] $end
$var wire 1 K this_re $end
$var parameter 2 L gi $end
$var reg 16 M this_dout [15:0] $end
$upscope $end
$scope begin g_bram[1] $end
$var wire 16 N this_addr [15:0] $end
$var wire 1 O this_re $end
$var parameter 2 P gi $end
$var reg 16 Q this_dout [15:0] $end
$upscope $end
$scope begin g_bram[2] $end
$var wire 16 R this_addr [15:0] $end
$var wire 1 S this_re $end
$var parameter 3 T gi $end
$var reg 16 U this_dout [15:0] $end
$upscope $end
$scope begin g_bram[3] $end
$var wire 16 V this_addr [15:0] $end
$var wire 1 W this_re $end
$var parameter 3 X gi $end
$var reg 16 Y this_dout [15:0] $end
$upscope $end
$scope module dut $end
$var wire 1 < clk $end
$var wire 1 = en $end
$var wire 16 Z h_hit_in [15:0] $end
$var wire 8 [ ix_in [7:0] $end
$var wire 8 \ iy_in [7:0] $end
$var wire 10 ] px_in [9:0] $end
$var wire 10 ^ py_in [9:0] $end
$var wire 1 C rst_n $end
$var wire 2 _ status_in [1:0] $end
$var wire 5 ` step_count_in [4:0] $end
$var wire 1 F valid_in $end
$var parameter 32 a DIR_F $end
$var parameter 32 b DIR_I $end
$var parameter 32 c DIR_W $end
$var parameter 32 d GRID_N $end
$var parameter 32 e H_F $end
$var parameter 32 f H_I $end
$var parameter 32 g H_W $end
$var parameter 32 h IDX_W $end
$var parameter 16 i NZ_CONST $end
$var parameter 32 j PX_W $end
$var parameter 32 k PY_W $end
$var parameter 32 l STEP_W $end
$var parameter 2 m ST_HIT $end
$var reg 16 n Nx_out [15:0] $end
$var reg 16 o Ny_out [15:0] $end
$var reg 16 p Nz_out [15:0] $end
$var reg 17 q dx_h_s3 [16:0] $end
$var reg 17 r dy_h_s3 [16:0] $end
$var reg 16 s h_hit_out [15:0] $end
$var reg 16 t h_xm_s2 [15:0] $end
$var reg 16 u h_xp_s2 [15:0] $end
$var reg 16 v h_ym_s2 [15:0] $end
$var reg 16 w h_yp_s2 [15:0] $end
$var reg 16 x hhit_s1 [15:0] $end
$var reg 16 y hhit_s2 [15:0] $end
$var reg 8 z ix_m1_s1 [7:0] $end
$var reg 8 { ix_out [7:0] $end
$var reg 8 | ix_p1_s1 [7:0] $end
$var reg 8 } ix_s1 [7:0] $end
$var reg 8 ~ ix_s2 [7:0] $end
$var reg 8 !" iy_m1_s1 [7:0] $end
$var reg 8 "" iy_out [7:0] $end
$var reg 8 #" iy_p1_s1 [7:0] $end
$var reg 8 $" iy_s1 [7:0] $end
$var reg 8 %" iy_s2 [7:0] $end
$var reg 16 &" nx_s3 [15:0] $end
$var reg 16 '" ny_s3 [15:0] $end
$var reg 10 (" px_out [9:0] $end
$var reg 10 )" px_s1 [9:0] $end
$var reg 10 *" px_s2 [9:0] $end
$var reg 10 +" py_out [9:0] $end
$var reg 10 ," py_s1 [9:0] $end
$var reg 10 -" py_s2 [9:0] $end
$var reg 2 ." stat_s1 [1:0] $end
$var reg 2 /" stat_s2 [1:0] $end
$var reg 2 0" status_out [1:0] $end
$var reg 5 1" step_count_out [4:0] $end
$var reg 5 2" step_s1 [4:0] $end
$var reg 5 3" step_s2 [4:0] $end
$var reg 1 4" v_s1 $end
$var reg 1 5" v_s2 $end
$var reg 1 ! valid_out $end
$scope function clamp_dec $end
$upscope $end
$scope function clamp_inc $end
$upscope $end
$scope function hdiff_to_dir $end
$upscope $end
$upscope $end
$scope begin $unm_blk_7 $end
$var integer 32 6" rec_i [31:0] $end
$upscope $end
$scope task run_one $end
$upscope $end
$upscope $end
$enddefinitions $end
$comment Show the parameter values. $end
$dumpall
b1 m
b101 l
b1010 k
b1010 j
b10000000000000 i
b1000 h
b10000 g
b100 f
b1011 e
b100000000 d
b10000 c
b10 b
b1101 a
b11 X
b10 T
b1 P
b0 L
b1100 ;
b1 :
b101 9
b1010 8
b1010 7
b100101100000000 6
b11001000000 5
b11 4
b1000 3
b10000 2
b100 1
b1011 0
b100000000 /
b10000 .
b10 -
b1101 ,
$end
#0
$dumpvars
b0 6"
x5"
x4"
bx 3"
bx 2"
bx 1"
bx 0"
bx /"
bx ."
bx -"
bx ,"
bx +"
bx *"
bx )"
bx ("
bx '"
bx &"
bx %"
bx $"
bx #"
bx ""
bx !"
bx ~
bx }
bx |
bx {
bx z
bx y
bx x
bx w
bx v
bx u
bx t
bx s
bx r
bx q
bx p
bx o
bx n
b0 `
b0 _
b0 ^
b0 ]
b0 \
b0 [
b0 Z
bx Y
xW
bx V
bx U
xS
bx R
bx Q
xO
bx N
bx M
xK
bx J
b0 I
b0 H
b0 G
0F
b0 E
b0 D
0C
b0 B
b0 A
b0 @
b0 ?
b0 >
1=
0<
bx +
bx *
bx )
bx (
bx '
bx &
bx %
bx $
bx #
bx "
x!
$end
#5000
04"
05"
0!
1<
#10000
0<
#15000
1<
#20000
0<
#25000
1<
#30000
0<
#35000
1<
#40000
0<
#45000
b1 #"
b0 !"
b1 |
b0 z
b0 ,"
b0 )"
b0 2"
b0 x
b0 $"
b0 }
b0 ."
b10000000000000 )
b10000000000000 p
b0 *
b0 o
b0 +
b0 n
1C
1<
#50000
0<
#55000
b0 -"
b0 *"
b0 3"
b0 y
b0 %"
b0 ~
b0 /"
1<
#60000
0<
#65000
b0 $
b0 +"
b0 %
b0 ("
b0 "
b0 1"
b0 (
b0 s
b0 &
b0 ""
b0 '
b0 {
b0 #
b0 0"
1<
#70000
1F
b11110000 B
b11110000 ^
b101000000 A
b101000000 ]
b101 E
b101 `
b101000101 >
b101000101 Z
b10000000 @
b10000000 \
b10000000 ?
b10000000 [
b1 D
b1 _
0<
#75000
b10000001 #"
b1111111 !"
b10000001 |
b1111111 z
14"
b11110000 ,"
b101000000 )"
b101 2"
b101000101 x
b10000000 $"
b10000000 }
b1 ."
1<
#80000
0F
0<
#85000
04"
15"
b11110000 -"
b101000000 *"
b101 3"
b101000101 y
b10000000 %"
b10000000 ~
b1 /"
1<
#90000
0<
#95000
bx *
bx o
bx +
bx n
1!
b11110000 $
b11110000 +"
b101000000 %
b101000000 ("
b101 "
b101 1"
b101000101 (
b101000101 s
b10000000 &
b10000000 ""
b10000000 '
b10000000 {
b1 #
b1 0"
05"
1<
#100000
0<
#105000
0!
b1 G
b1 I
1<
#110000
0<
#115000
1<
#120000
0<
#125000
1<
#130000
0<
#135000
1<
#140000
0<
#145000
1<
#150000
0<
#155000
b1 6"
1<
#160000
1F
b0 B
b0 ^
b0 A
b0 ]
b1 E
b1 `
b1110100100 >
b1110100100 Z
b0 @
b0 \
b0 ?
b0 [
0<
#165000
b1 #"
b0 !"
b1 |
b0 z
14"
b0 ,"
b0 )"
b1 2"
b1110100100 x
b0 $"
b0 }
1<
#170000
0F
0<
#175000
15"
b0 -"
b0 *"
b1 3"
b1110100100 y
b0 %"
b0 ~
04"
1<
#180000
0<
#185000
05"
1!
b0 $
b0 +"
b0 %
b0 ("
b1 "
b1 1"
b1110100100 (
b1110100100 s
b0 &
b0 ""
b0 '
b0 {
1<
#190000
0<
#195000
0!
b10 G
b10 I
1<
#200000
0<
#205000
1<
#210000
0<
#215000
1<
#220000
0<
#225000
1<
#230000
0<
#235000
1<
#240000
0<
#245000
b10 6"
1<
#250000
1F
b111011111 B
b111011111 ^
b1001111111 A
b1001111111 ]
b10000 E
b10000 `
b1111111010101000 >
b1111111010101000 Z
b11111111 @
b11111111 \
b11111111 ?
b11111111 [
0<
#255000
b11111111 #"
b11111110 !"
b11111111 |
b11111110 z
14"
b111011111 ,"
b1001111111 )"
b10000 2"
b1111111010101000 x
b11111111 $"
b11111111 }
1<
#260000
0F
0<
#265000
04"
15"
b111011111 -"
b1001111111 *"
b10000 3"
b1111111010101000 y
b11111111 %"
b11111111 ~
1<
#270000
0<
#275000
1!
b111011111 $
b111011111 +"
b1001111111 %
b1001111111 ("
b10000 "
b10000 1"
b1111111010101000 (
b1111111010101000 s
b11111111 &
b11111111 ""
b11111111 '
b11111111 {
05"
1<
#280000
0<
#285000
0!
b11 G
b11 I
1<
#290000
0<
#295000
1<
#300000
0<
#305000
1<
#310000
0<
#315000
1<
#320000
0<
#325000
1<
#330000
0<
#335000
b11 6"
1<
#340000
1F
b11110000 B
b11110000 ^
b101000000 A
b101000000 ]
b0 >
b0 Z
b10000000 @
b10000000 \
b10000000 ?
b10000000 [
b0 D
b0 _
0<
#345000
b10000001 #"
b1111111 !"
b10000001 |
b1111111 z
14"
b11110000 ,"
b101000000 )"
b0 x
b10000000 $"
b10000000 }
b0 ."
1<
#350000
0F
0<
#355000
15"
b11110000 -"
b101000000 *"
b0 y
b10000000 %"
b10000000 ~
b0 /"
04"
1<
#360000
0<
#365000
05"
b0 *
b0 o
b0 +
b0 n
1!
b11110000 $
b11110000 +"
b101000000 %
b101000000 ("
b0 (
b0 s
b10000000 &
b10000000 ""
b10000000 '
b10000000 {
b0 #
b0 0"
1<
#370000
0<
#375000
0!
b1 H
b100 I
1<
#380000
0<
#385000
1<
#390000
0<
#395000
1<
#400000
0<
#405000
1<
#410000
0<
#415000
1<
#420000
0<
#425000
b100 6"
1<
#430000
1F
b1100100 B
b1100100 ^
b1100100 A
b1100100 ]
b1000 E
b1000 `
b110010 @
b110010 \
b11001000 ?
b11001000 [
b10 D
b10 _
0<
#435000
b110011 #"
b110001 !"
b11001001 |
b11000111 z
14"
b1100100 ,"
b1100100 )"
b1000 2"
b110010 $"
b11001000 }
b10 ."
1<
#440000
0F
0<
#445000
04"
15"
b1100100 -"
b1100100 *"
b1000 3"
b110010 %"
b11001000 ~
b10 /"
1<
#450000
0<
#455000
1!
b1100100 $
b1100100 +"
b1100100 %
b1100100 ("
b1000 "
b1000 1"
b110010 &
b110010 ""
b11001000 '
b11001000 {
b10 #
b10 0"
05"
1<
#460000
0<
#465000
0!
b10 H
b101 I
1<
#470000
0<
#475000
1<
#480000
0<
#485000
1<
#490000
0<
#495000
1<
#500000
0<
#505000
1<
#510000
0<
#515000
b101 6"
1<
#520000
1F
b1111110100 B
b1111110100 ^
b101010110 A
b101010110 ]
b111 E
b111 `
b110100 >
b110100 Z
b1101000 @
b1101000 \
b11111010 ?
b11111010 [
b1 D
b1 _
0<
#525000
b1101001 #"
b1100111 !"
b11111011 |
b11111001 z
14"
b1111110100 ,"
b101010110 )"
b111 2"
b110100 x
b1101000 $"
b11111010 }
b1 ."
1<
#530000
0F
0<
#535000
15"
b1111110100 -"
b101010110 *"
b111 3"
b110100 y
b1101000 %"
b11111010 ~
b1 /"
04"
1<
#540000
0<
#545000
05"
bx *
bx o
bx +
bx n
1!
b1111110100 $
b1111110100 +"
b101010110 %
b101010110 ("
b111 "
b111 1"
b110100 (
b110100 s
b1101000 &
b1101000 ""
b11111010 '
b11111010 {
b1 #
b1 0"
1<
#550000
0<
#555000
0!
b100 G
b110 I
1<
#560000
0<
#565000
1<
#570000
0<
#575000
1<
#580000
0<
#585000
1<
#590000
0<
#595000
1<
#600000
0<
#605000
b110 6"
1<
#610000
1F
b100100101 B
b100100101 ^
b1000110000 A
b1000110000 ]
b11101 E
b11101 `
b1111111011001100 >
b1111111011001100 Z
b1010010 @
b1010010 \
b1100000 ?
b1100000 [
0<
#615000
b1010011 #"
b1010001 !"
b1100001 |
b1011111 z
14"
b100100101 ,"
b1000110000 )"
b11101 2"
b1111111011001100 x
b1010010 $"
b1100000 }
1<
#620000
0F
0<
#625000
04"
15"
b100100101 -"
b1000110000 *"
b11101 3"
b1111111011001100 y
b1010010 %"
b1100000 ~
1<
#630000
0<
#635000
1!
b100100101 $
b100100101 +"
b1000110000 %
b1000110000 ("
b11101 "
b11101 1"
b1111111011001100 (
b1111111011001100 s
b1010010 &
b1010010 ""
b1100000 '
b1100000 {
05"
1<
#640000
0<
#645000
0!
b101 G
b111 I
1<
#650000
0<
#655000
1<
#660000
0<
#665000
1<
#670000
0<
#675000
1<
#680000
0<
#685000
1<
#690000
0<
#695000
b111 6"
1<
#700000
1F
b100101111 B
b100101111 ^
b1110100001 A
b1110100001 ]
b1100 E
b1100 `
b1111110000010010 >
b1111110000010010 Z
b1000010 @
b1000010 \
b10010000 ?
b10010000 [
0<
#705000
b1000011 #"
b1000001 !"
b10010001 |
b10001111 z
14"
b100101111 ,"
b1110100001 )"
b1100 2"
b1111110000010010 x
b1000010 $"
b10010000 }
1<
#710000
0F
0<
#715000
15"
b100101111 -"
b1110100001 *"
b1100 3"
b1111110000010010 y
b1000010 %"
b10010000 ~
04"
1<
#720000
0<
#725000
05"
1!
b100101111 $
b100101111 +"
b1110100001 %
b1110100001 ("
b1100 "
b1100 1"
b1111110000010010 (
b1111110000010010 s
b1000010 &
b1000010 ""
b10010000 '
b10010000 {
1<
#730000
0<
#735000
0!
b110 G
b1000 I
1<
#740000
0<
#745000
1<
#750000
0<
#755000
1<
#760000
0<
#765000
1<
#770000
0<
#775000
1<
#780000
0<
#785000
b1000 6"
1<
#790000
1F
b1101110111 B
b1101110111 ^
b101101111 A
b101101111 ]
b1010 E
b1010 `
b1111111001000100 >
b1111111001000100 Z
b1001 @
b1001 \
b1001010 ?
b1001010 [
0<
#795000
b1010 #"
b1000 !"
b1001011 |
b1001001 z
14"
b1101110111 ,"
b101101111 )"
b1010 2"
b1111111001000100 x
b1001 $"
b1001010 }
1<
#800000
0F
0<
#805000
04"
15"
b1101110111 -"
b101101111 *"
b1010 3"
b1111111001000100 y
b1001 %"
b1001010 ~
1<
#810000
0<
#815000
1!
b1101110111 $
b1101110111 +"
b101101111 %
b101101111 ("
b1010 "
b1010 1"
b1111111001000100 (
b1111111001000100 s
b1001 &
b1001 ""
b1001010 '
b1001010 {
05"
1<
#820000
0<
#825000
0!
b111 G
b1001 I
1<
#830000
0<
#835000
1<
#840000
0<
#845000
1<
#850000
0<
#855000
1<
#860000
0<
#865000
1<
#870000
0<
#875000
b1001 6"
1<
