src/hdl/shader.sv
module shader #(
    parameter int H_W        = 16,
    parameter int H_I        = 4,
    parameter int H_F        = H_W - 1 - H_I,
    parameter int DIR_W      = 16,
    parameter int DIR_I      = 2,
    parameter int DIR_F      = DIR_W - 1 - DIR_I,
    parameter int N_STEPS    = 16,
    parameter int STEP_W     = $clog2(N_STEPS + 1),
    parameter int PX_W       = 10,
    parameter int PY_W       = 10,
    parameter logic [7:0] SKY_R = 8'd135,
    parameter logic [7:0] SKY_G = 8'd206,
    parameter logic [7:0] SKY_B = 8'd235,
    parameter logic [7:0] PALE_R   = 8'd192,
    parameter logic [7:0] PALE_G   = 8'd192,
    parameter logic [7:0] PALE_B   = 8'd192,
    parameter logic [7:0] AMBIENT  = 8'd64
)(
    input  logic                       clk,
    input  logic                       rst_n,
    input  logic                       en,

    input  logic [1:0]                 status_in,
    input  logic signed [H_W-1:0]      h_hit_in,
    input  logic [STEP_W-1:0]          step_count_in,
    input  logic signed [DIR_W-1:0]    Nx_in,
    input  logic signed [DIR_W-1:0]    Ny_in,
    input  logic signed [DIR_W-1:0]    Nz_in,
    input  logic [PX_W-1:0]            px_in,
    input  logic [PY_W-1:0]            py_in,
    input  logic                       valid_in,

    input  logic signed [DIR_W-1:0]    sun_dx,
    input  logic signed [DIR_W-1:0]    sun_dy,
    input  logic signed [DIR_W-1:0]    sun_dz,

    output logic [7:0]                 r_out,
    output logic [7:0]                 g_out,
    output logic [7:0]                 b_out,
    output logic [PX_W-1:0]            px_out,
    output logic [PY_W-1:0]            py_out,
    output logic                       valid_out
);

    localparam logic [1:0] ST_HIT = 2'b01;

    // ---- Dot product N·L ----
    logic signed [2*DIR_W-1:0] dot_x, dot_y, dot_z;
    logic signed [2*DIR_W:0]   dot_sum;
    logic signed [2*DIR_W-1:0] bright_q;

    // ---- 8-bit intermediates ----
    logic [7:0] altitude_u8;
    logic [7:0] fog_u8;
    logic [7:0] bright_u8;
    logic [7:0] light_u8;
    logic [7:0] base_r, base_g, base_b;
    logic [7:0] fogged_r, fogged_g, fogged_b;
    logic [7:0] lit_r, lit_g, lit_b;

    // ---- Scratch integers for arithmetic ----
    integer altitude_shifted;
    integer fog_int;
    integer bright_tmp;
    integer mix_r_acc, mix_g_acc, mix_b_acc;
    integer mul_r_prod, mul_g_prod, mul_b_prod;

    always_comb begin
        // =====================================================
        // BLOCK A: Lambert dot product N·L
        // =====================================================

        // Sun is hardcoded to (0, 0, 1) → dot product reduces to Nz.
        // bright_q is in the same Q-format as Nz (Q2.13).  Pad with zeros
        // on the left to match the 2*DIR_W-bit width that bright_to_u8 expects.

        if (Nz_in <= 0)
            bright_q = '0;
        else
            bright_q = {{DIR_W{1'b0}}, Nz_in};

        // =====================================================
        // BLOCK B: brightness Q-format → 8-bit, then ambient blend
        // =====================================================
        // ---- bright_to_u8 inlined ----
        if (bright_q[2*DIR_W-1])
            bright_tmp = 0;
        else if (bright_q >= (1 <<< DIR_F))
            bright_tmp = 255;
        else if (DIR_F >= 8)
            bright_tmp = bright_q >>> (DIR_F - 8);
        else
            bright_tmp = bright_q <<< (8 - DIR_F);

        // clamp_u8 inlined
        if (bright_tmp < 0)         bright_u8 = 8'd0;
        else if (bright_tmp > 255)  bright_u8 = 8'd255;
        else                        bright_u8 = bright_tmp[7:0];

        // Ambient blend: light_u8 = AMBIENT + ((255 - AMBIENT) * bright_u8) >> 8
        light_u8 = AMBIENT + (((16'd255 - AMBIENT) * bright_u8) >> 8);

        // =====================================================
        // BLOCK C: height → altitude_u8 → base RGB
        // =====================================================
        // ---- height_to_u8 inlined ----
        if (H_F >= 7)
            altitude_shifted = (h_hit_in >>> (H_F - 7)) + 128;
        else
            altitude_shifted = (h_hit_in <<< (7 - H_F)) + 128;

        // clamp_u8 inlined
        if (altitude_shifted < 0)        altitude_u8 = 8'd0;
        else if (altitude_shifted > 255) altitude_u8 = 8'd255;
        else                             altitude_u8 = altitude_shifted[7:0];

        // Height LUT: low=blue, high=red, mid=greenish
        base_r = altitude_u8;
        base_b = 8'd255 - altitude_u8;
        base_g = 8'd32 + ((8'd255 - ((altitude_u8 > 8'd127) ?
                 ((altitude_u8 - 8'd127) << 1) :
                 ((8'd127 - altitude_u8) << 1))) >> 2);

        // =====================================================
        // BLOCK D: step_count → fog
        // =====================================================
        // ---- step_to_fog inlined ----
        if (N_STEPS <= 1)
            fog_int = 0;
        else
            fog_int = (step_count_in * 255) / N_STEPS;

        // clamp_u8 inlined
        if (fog_int < 0)        fog_u8 = 8'd0;
        else if (fog_int > 255) fog_u8 = 8'd255;
        else                    fog_u8 = fog_int[7:0];

        // =====================================================
        // BLOCK E: composition — mix(base, PALE, fog) then mul(fogged, light)
        // =====================================================
        // ---- mix_u8 inlined for r/g/b ----
        mix_r_acc = ((255 - fog_u8) * base_r + fog_u8 * PALE_R) >> 8;
        mix_g_acc = ((255 - fog_u8) * base_g + fog_u8 * PALE_G) >> 8;
        mix_b_acc = ((255 - fog_u8) * base_b + fog_u8 * PALE_B) >> 8;

        // clamp_u8 inlined
        if (mix_r_acc < 0)        fogged_r = 8'd0;
        else if (mix_r_acc > 255) fogged_r = 8'd255;
        else                      fogged_r = mix_r_acc[7:0];

        if (mix_g_acc < 0)        fogged_g = 8'd0;
        else if (mix_g_acc > 255) fogged_g = 8'd255;
        else                      fogged_g = mix_g_acc[7:0];

        if (mix_b_acc < 0)        fogged_b = 8'd0;
        else if (mix_b_acc > 255) fogged_b = 8'd255;
        else                      fogged_b = mix_b_acc[7:0];

        // ---- mul_u8 inlined for r/g/b ----
        mul_r_prod = (fogged_r * light_u8) >> 8;
        mul_g_prod = (fogged_g * light_u8) >> 8;
        mul_b_prod = (fogged_b * light_u8) >> 8;

        if (mul_r_prod < 0)        lit_r = 8'd0;
        else if (mul_r_prod > 255) lit_r = 8'd255;
        else                       lit_r = mul_r_prod[7:0];

        if (mul_g_prod < 0)        lit_g = 8'd0;
        else if (mul_g_prod > 255) lit_g = 8'd255;
        else                       lit_g = mul_g_prod[7:0];

        if (mul_b_prod < 0)        lit_b = 8'd0;
        else if (mul_b_prod > 255) lit_b = 8'd255;
        else                       lit_b = mul_b_prod[7:0];
    end

    // =====================================================
    // BLOCK F: output register with MUX HIT vs sky
    // =====================================================
    always_ff @(posedge clk) begin
        if (!rst_n) begin
            valid_out <= 1'b0;
        end else if (en) begin
            px_out    <= px_in;
            py_out    <= py_in;
            valid_out <= valid_in;

            if (status_in == ST_HIT) begin
                r_out <= lit_r;
                g_out <= lit_g;
                b_out <= lit_b;
            end else begin
                r_out <= SKY_R;
                g_out <= SKY_G;
                b_out <= SKY_B;
            end
        end
    end

endmodule

src/tb/tb_shader.sv
// ============================================================================
//  tb_shader.sv
//  ----------------------------------------------------------------------------
//  Sequential testbench for shader.sv.
//
//  Drives one record at a time, waits for valid_out, compares:
//      - r_out, g_out, b_out  (allow +/-1 LSB)
//      - px_out, py_out       (must pass through)
//
//  No BRAM in this module — pure arithmetic.
//
//  Run:
//      iverilog -g2012 -o tb_shader.vvp tb_shader.sv ../shader.sv
//      vvp tb_shader.vvp
// ============================================================================
`timescale 1ns/1ps

module tb_shader;

    localparam int H_W     = 16;
    localparam int H_I     = 4;
    localparam int H_F     = H_W - 1 - H_I;
    localparam int DIR_W   = 16;
    localparam int DIR_I   = 2;
    localparam int DIR_F   = DIR_W - 1 - DIR_I;
    localparam int N_STEPS = 16;
    localparam int STEP_W  = 5;
    localparam int PX_W    = 10;
    localparam int PY_W    = 10;

    localparam int LATENCY = 1;     // shader is 1 cycle
    localparam int TOLER   = 1;

    localparam int VPR     = 14;
    localparam int MAX_REC = 2100;
    localparam int MEM_SZ  = MAX_REC * VPR;

    logic clk = 0;
    logic rst_n = 0;
    always #5 clk = ~clk;

    logic                       en;
    logic [1:0]                 status_in;
    logic signed [H_W-1:0]      h_hit_in;
    logic [STEP_W-1:0]          step_count_in;
    logic signed [DIR_W-1:0]    Nx_in, Ny_in, Nz_in;
    logic [PX_W-1:0]            px_in;
    logic [PY_W-1:0]            py_in;
    logic                       valid_in;
    logic signed [DIR_W-1:0]    sun_dx, sun_dy, sun_dz;
    logic [7:0]                 r_out, g_out, b_out;
    logic [PX_W-1:0]            px_out;
    logic [PY_W-1:0]            py_out;
    logic                       valid_out;

    shader dut (.*);

    logic [15:0] vectors [0:MEM_SZ-1];

    int n_tests, n_pass, n_fail;

    function automatic int abs_diff_u8(input logic [7:0] a, input logic [7:0] b);
        int d;
        d = int'(a) - int'(b);
        return (d < 0) ? -d : d;
    endfunction

    task automatic run_one(input int rec_i);
        int base;
        int waited;
        logic [1:0]              in_status;
        logic signed [H_W-1:0]   in_h_hit;
        logic [STEP_W-1:0]       in_step;
        logic signed [DIR_W-1:0] in_Nx, in_Ny, in_Nz;
        logic signed [DIR_W-1:0] in_sx, in_sy, in_sz;
        logic [PX_W-1:0]         in_px;
        logic [PY_W-1:0]         in_py;
        logic [7:0]              e_r, e_g, e_b;
        bit ok;

        base = rec_i * VPR;

        @(negedge clk);
        in_status = vectors[base + 0][1:0];
        in_h_hit  = vectors[base + 1];
        in_step   = vectors[base + 2][STEP_W-1:0];
        in_Nx     = vectors[base + 3];
        in_Ny     = vectors[base + 4];
        in_Nz     = vectors[base + 5];
        in_sx     = vectors[base + 6];
        in_sy     = vectors[base + 7];
        in_sz     = vectors[base + 8];
        in_px     = vectors[base + 9][PX_W-1:0];
        in_py     = vectors[base + 10][PY_W-1:0];
        e_r       = vectors[base + 11][7:0];
        e_g       = vectors[base + 12][7:0];
        e_b       = vectors[base + 13][7:0];

        status_in     = in_status;
        h_hit_in      = in_h_hit;
        step_count_in = in_step;
        Nx_in         = in_Nx;
        Ny_in         = in_Ny;
        Nz_in         = in_Nz;
        sun_dx        = in_sx;
        sun_dy        = in_sy;
        sun_dz        = in_sz;
        px_in         = in_px;
        py_in         = in_py;




        valid_in = 1;

        // Debug: dump combinational internals while inputs are still applied
        if (rec_i == 0) begin
            #1;  // small delay to let combinational logic settle
            $display("=== Rec 0 internal trace ===");
            $display("  bright_q     = %0d", $signed(dut.bright_q));
            $display("  bright_u8    = %0d", dut.bright_u8);
            $display("  light_u8     = %0d", dut.light_u8);
            $display("  altitude_u8  = %0d", dut.altitude_u8);
            $display("  base   r,g,b = %0d, %0d, %0d", dut.base_r, dut.base_g, dut.base_b);
            $display("  fog_u8       = %0d", dut.fog_u8);
            $display("  fogged r,g,b = %0d, %0d, %0d", dut.fogged_r, dut.fogged_g, dut.fogged_b);
            $display("  lit    r,g,b = %0d, %0d, %0d", dut.lit_r, dut.lit_g, dut.lit_b);
        end

        @(negedge clk);
        valid_in = 0;

        waited = 0;
        while (!valid_out && waited < 2*LATENCY + 5) begin
            @(posedge clk);
            waited++;
        end

        if (!valid_out) begin
            $display("rec %0d: TIMEOUT waiting for valid_out", rec_i);
            n_fail++;
        end else begin
            n_tests++;
            ok = 1;
            if (abs_diff_u8(r_out, e_r) > TOLER) ok = 0;
            if (abs_diff_u8(g_out, e_g) > TOLER) ok = 0;
            if (abs_diff_u8(b_out, e_b) > TOLER) ok = 0;
            if (px_out !== in_px) ok = 0;
            if (py_out !== in_py) ok = 0;

            if (ok) n_pass++;
            else begin
                n_fail++;
                if (n_fail <= 10) begin
                    $display("rec %0d FAIL:", rec_i);
                    $display("  in:  stat=%0d h=%0d step=%0d N=(%0d,%0d,%0d) sun=(%0d,%0d,%0d)",
                             in_status, $signed(in_h_hit), in_step,
                             $signed(in_Nx), $signed(in_Ny), $signed(in_Nz),
                             $signed(in_sx), $signed(in_sy), $signed(in_sz));
                    $display("  got: rgb=(%0d,%0d,%0d) px=%0d py=%0d",
                             r_out, g_out, b_out, px_out, py_out);
                    $display("  exp: rgb=(%0d,%0d,%0d)", e_r, e_g, e_b);
                end
            end
        end

        repeat (LATENCY + 1) @(posedge clk);
    endtask

    initial begin
        int rec_i;
        $dumpfile("tb_shader.vcd");
        $dumpvars(0, tb_shader);

        en = 1;
        status_in = 0; h_hit_in = 0; step_count_in = 0;
        Nx_in = 0; Ny_in = 0; Nz_in = 0;
        sun_dx = 0; sun_dy = 0; sun_dz = 0;
        px_in = 0; py_in = 0; valid_in = 0;
        n_tests = 0; n_pass = 0; n_fail = 0;

        $readmemh("shader_vectors.hex", vectors);

        rst_n = 0;
        repeat (5) @(posedge clk);
        rst_n = 1;
        repeat (2) @(posedge clk);

        rec_i = 0;
        while (rec_i < MAX_REC && (^vectors[rec_i*VPR] !== 1'bx)) begin
            run_one(rec_i);
            rec_i++;
        end

        $display("================================================");
        $display("shader TB: tested=%0d  pass=%0d  fail=%0d",
                 n_tests, n_pass, n_fail);
        if (n_fail == 0 && n_tests > 0)
            $display("RESULT: PASS");
        else
            $display("RESULT: FAIL");
        $display("================================================");
        $finish;
    end

    initial begin
        #200_000_000;
        $display("WATCHDOG TIMEOUT");
        $finish;
    end

endmodule

src/tb/tb_shader.vcd
$date
	Sun May 24 11:46:58 2026
$end
$version
	Icarus Verilog
$end
$timescale
	1ps
$end
$scope module tb_shader $end
$var wire 1 ! valid_out $end
$var wire 8 " r_out [7:0] $end
$var wire 10 # py_out [9:0] $end
$var wire 10 $ px_out [9:0] $end
$var wire 8 % g_out [7:0] $end
$var wire 8 & b_out [7:0] $end
$var parameter 32 ' DIR_F $end
$var parameter 32 ( DIR_I $end
$var parameter 32 ) DIR_W $end
$var parameter 32 * H_F $end
$var parameter 32 + H_I $end
$var parameter 32 , H_W $end
$var parameter 32 - LATENCY $end
$var parameter 32 . MAX_REC $end
$var parameter 32 / MEM_SZ $end
$var parameter 32 0 N_STEPS $end
$var parameter 32 1 PX_W $end
$var parameter 32 2 PY_W $end
$var parameter 32 3 STEP_W $end
$var parameter 32 4 TOLER $end
$var parameter 32 5 VPR $end
$var reg 16 6 Nx_in [15:0] $end
$var reg 16 7 Ny_in [15:0] $end
$var reg 16 8 Nz_in [15:0] $end
$var reg 1 9 clk $end
$var reg 1 : en $end
$var reg 16 ; h_hit_in [15:0] $end
$var reg 10 < px_in [9:0] $end
$var reg 10 = py_in [9:0] $end
$var reg 1 > rst_n $end
$var reg 2 ? status_in [1:0] $end
$var reg 5 @ step_count_in [4:0] $end
$var reg 16 A sun_dx [15:0] $end
$var reg 16 B sun_dy [15:0] $end
$var reg 16 C sun_dz [15:0] $end
$var reg 1 D valid_in $end
$var integer 32 E n_fail [31:0] $end
$var integer 32 F n_pass [31:0] $end
$var integer 32 G n_tests [31:0] $end
$scope function abs_diff_u8 $end
$upscope $end
$scope module dut $end
$var wire 16 H Nx_in [15:0] $end
$var wire 16 I Ny_in [15:0] $end
$var wire 16 J Nz_in [15:0] $end
$var wire 1 9 clk $end
$var wire 1 : en $end
$var wire 16 K h_hit_in [15:0] $end
$var wire 10 L px_in [9:0] $end
$var wire 10 M py_in [9:0] $end
$var wire 1 > rst_n $end
$var wire 2 N status_in [1:0] $end
$var wire 5 O step_count_in [4:0] $end
$var wire 16 P sun_dx [15:0] $end
$var wire 16 Q sun_dy [15:0] $end
$var wire 16 R sun_dz [15:0] $end
$var wire 1 D valid_in $end
$var parameter 8 S AMBIENT $end
$var parameter 32 T DIR_F $end
$var parameter 32 U DIR_I $end
$var parameter 32 V DIR_W $end
$var parameter 32 W H_F $end
$var parameter 32 X H_I $end
$var parameter 32 Y H_W $end
$var parameter 32 Z N_STEPS $end
$var parameter 8 [ PALE_B $end
$var parameter 8 \ PALE_G $end
$var parameter 8 ] PALE_R $end
$var parameter 32 ^ PX_W $end
$var parameter 32 _ PY_W $end
$var parameter 8 ` SKY_B $end
$var parameter 8 a SKY_G $end
$var parameter 8 b SKY_R $end
$var parameter 32 c STEP_W $end
$var parameter 2 d ST_HIT $end
$var reg 8 e altitude_u8 [7:0] $end
$var reg 8 f b_out [7:0] $end
$var reg 8 g base_b [7:0] $end
$var reg 8 h base_g [7:0] $end
$var reg 8 i base_r [7:0] $end
$var reg 32 j bright_q [31:0] $end
$var reg 8 k bright_u8 [7:0] $end
$var reg 8 l fog_u8 [7:0] $end
$var reg 8 m fogged_b [7:0] $end
$var reg 8 n fogged_g [7:0] $end
$var reg 8 o fogged_r [7:0] $end
$var reg 8 p g_out [7:0] $end
$var reg 8 q light_u8 [7:0] $end
$var reg 8 r lit_b [7:0] $end
$var reg 8 s lit_g [7:0] $end
$var reg 8 t lit_r [7:0] $end
$var reg 10 u px_out [9:0] $end
$var reg 10 v py_out [9:0] $end
$var reg 8 w r_out [7:0] $end
$var reg 1 ! valid_out $end
$var integer 32 x altitude_shifted [31:0] $end
$var integer 32 y bright_tmp [31:0] $end
$var integer 32 z fog_int [31:0] $end
$var integer 32 { mix_b_acc [31:0] $end
$var integer 32 | mix_g_acc [31:0] $end
$var integer 32 } mix_r_acc [31:0] $end
$var integer 32 ~ mul_b_prod [31:0] $end
$var integer 32 !" mul_g_prod [31:0] $end
$var integer 32 "" mul_r_prod [31:0] $end
$upscope $end
$scope begin $unm_blk_7 $end
$var integer 32 #" rec_i [31:0] $end
$upscope $end
$scope task run_one $end
$upscope $end
$upscope $end
$enddefinitions $end
$comment Show the parameter values. $end
$dumpall
b1 d
b101 c
b10000111 b
b11001110 a
b11101011 `
b1010 _
b1010 ^
b11000000 ]
b11000000 \
b11000000 [
b10000 Z
b10000 Y
b100 X
b1011 W
b10000 V
b10 U
b1101 T
b1000000 S
b1110 5
b1 4
b101 3
b1010 2
b1010 1
b10000 0
b111001011011000 /
b100000110100 .
b1 -
b10000 ,
b100 +
b1011 *
b10000 )
b10 (
b1101 '
$end
#0
$dumpvars
b0 #"
b11111 ""
b10111 !"
b11111 ~
b1111111 }
b1011110 |
b1111110 {
b0 z
b0 y
b10000000 x
bx w
bx v
bx u
b11111 t
b10111 s
b11111 r
b1000000 q
bx p
b1111111 o
b1011110 n
b1111110 m
b0 l
b0 k
b0 j
b10000000 i
b1011111 h
b1111111 g
bx f
b10000000 e
b0 R
b0 Q
b0 P
b0 O
b0 N
b0 M
b0 L
b0 K
b0 J
b0 I
b0 H
b0 G
b0 F
b0 E
0D
b0 C
b0 B
b0 A
b0 @
b0 ?
0>
b0 =
b0 <
b0 ;
1:
09
b0 8
b0 7
b0 6
bx &
bx %
bx $
bx #
bx "
x!
$end
#5000
0!
19
#10000
09
#15000
19
#20000
09
#25000
19
#30000
09
#35000
19
#40000
09
#45000
b11101011 &
b11101011 f
b11001110 %
b11001110 p
b10000111 "
b10000111 w
b0 #
b0 v
b0 $
b0 u
1>
19
#50000
09
#55000
19
#60000
09
#65000
19
#70000
b1111101 r
b1011101 s
b1111110 t
b1111101 ~
b1011101 !"
b1111110 ""
b11111110 q
b11111111 k
b11111111 y
b10000000000000 j
1D
b11110000 =
b11110000 M
b101000000 <
b101000000 L
b10000000000000 C
b10000000000000 R
b10000000000000 8
b10000000000000 J
b1 ?
b1 N
09
#75000
b1111101 &
b1111101 f
b1011101 %
b1011101 p
b1111110 "
b1111110 w
1!
b11110000 #
b11110000 v
b101000000 $
b101000000 u
19
#80000
b1 F
b1 G
0D
09
#85000
0!
19
#90000
09
#95000
b1 #"
19
#100000
1D
b0 C
b0 R
b10000000000000 A
b10000000000000 P
09
#105000
1!
19
#110000
b1 E
b10 G
0D
09
#115000
0!
19
#120000
09
#125000
b10 #"
19
#130000
1D
b10000000000000 C
b10000000000000 R
b0 A
b0 P
b0 ?
b0 N
09
#135000
b11101011 &
b11101011 f
b11001110 %
b11001110 p
b10000111 "
b10000111 w
1!
19
#140000
b10 F
b11 G
0D
09
#145000
0!
19
#150000
09
#155000
b11 #"
19
#160000
1D
b10 ?
b10 N
09
#165000
1!
19
#170000
b11 F
b100 G
0D
09
#175000
0!
19
#180000
09
#185000
b100 #"
19
#190000
b11000000 r
b10110011 s
b10110010 t
b11000000 ~
b10110011 !"
b10110010 ""
b11000010 m
b10110101 n
b10110100 o
b11000010 {
b10110101 |
b10110100 }
b11101111 l
b11101111 z
b100110 h
b11110011 g
b1100 i
b1100 e
b1100 x
1D
b110010000 =
b110010000 M
b1100100 <
b1100100 L
b1111 @
b1111 O
b1111100011001101 ;
b1111100011001101 K
b1 ?
b1 N
09
#195000
b11000000 &
b11000000 f
b10110011 %
b10110011 p
b10110010 "
b10110010 w
1!
b110010000 #
b110010000 v
b1100100 $
b1100100 u
19
#200000
b100 F
b101 G
0D
09
#205000
0!
19
#210000
09
#215000
b101 #"
19
#220000
b10101 r
b101100 s
b11101101 t
b10101 ~
b101100 !"
b11101101 ""
b10110 m
b101101 n
b11101111 o
b10110 {
b101101 |
b11101111 }
b1111 l
b1111 z
b100101 h
b1100 g
b11110011 i
b11110011 e
b11110011 x
1D
b11001000 =
b11001000 M
b111110100 <
b111110100 L
b1 @
b1 O
b11100110011 ;
b11100110011 K
09
#225000
b10101 &
b10101 f
b101100 %
b101100 p
b11101101 "
b11101101 w
1!
b11001000 #
b11001000 v
b111110100 $
b111110100 u
19
#230000
b101 F
b110 G
0D
09
#235000
0!
19
#240000
09
#245000
b110 #"
19
#250000
b1000101 r
b1000101 s
b1000101 t
b1000101 ~
b1000101 !"
b1000101 ""
b10111111 m
b10111111 n
b10111111 o
b10111111 {
b10111111 |
b10111111 }
b11111111 l
b100011110 z
b101001 h
b10011 g
b11101100 i
b11101100 e
b11101100 x
b1011101 q
b101000 k
b101000 y
b10100010101 j
1D
b110100001 =
b110100001 M
b10100000 <
b10100000 L
b10100010101 8
b10100010101 J
b10110100100 7
b10110100100 I
b1110100001000110 6
b1110100001000110 H
b10010 @
b10010 O
b11011000110 ;
b11011000110 K
09
#255000
b1000101 &
b1000101 f
b1000101 %
b1000101 p
b1000101 "
b1000101 w
1!
b110100001 #
b110100001 v
b10100000 $
b10100000 u
19
#260000
b110 F
b111 G
0D
09
#265000
0!
19
#270000
09
#275000
b111 #"
19
#280000
b1011001 r
b1011001 s
b1011001 t
b1011001 ~
b1011001 !"
b1011001 ""
b101101110 z
b110100 h
b101010 g
b11010101 i
b11010101 e
b11010101 x
b1111000 q
b1001100 k
b1001100 y
b100110001000 j
1D
b1110001 =
b1110001 M
b11110100 <
b11110100 L
b100110001000 8
b100110001000 J
b1111100001010100 7
b1111100001010100 I
b111001100011 6
b111001100011 H
b10111 @
b10111 O
b10101010001 ;
b10101010001 K
09
#285000
b1011001 &
b1011001 f
b1011001 %
b1011001 p
b1011001 "
b1011001 w
1!
b1110001 #
b1110001 v
b11110100 $
b11110100 u
19
#290000
b111 F
b1000 G
0D
09
#295000
0!
19
#300000
09
#305000
b1000 #"
19
#310000
b110011 r
b11111 s
b11101 t
b110011 ~
b11111 !"
b11101 ""
b11001110 m
b1111111 n
b1110111 o
b11001110 {
b1111111 |
b1110111 }
b10001111 l
b10001111 z
b101110 h
b11100010 g
b11101 i
b11101 e
b11101 x
b1000000 q
b0 k
b0 y
b0 j
1D
b100110 =
b100110 M
b1100 <
b1100 L
b1110111100100010 8
b1110111100100010 J
b1000010110011 7
b1000010110011 I
b1111100101110 6
b1111100101110 H
b1001 @
b1001 O
b1111100111011000 ;
b1111100111011000 K
09
#315000
b110011 &
b110011 f
b11111 %
b11111 p
b11101 "
b11101 w
1!
b100110 #
b100110 v
b1100 $
b1100 u
19
#320000
b1000 F
b1001 G
0D
09
#325000
0!
19
#330000
09
#335000
b1001 #"
19
#340000
b101111 r
b101111 s
b101111 t
b101111 ~
b101111 !"
b101111 ""
b10111111 m
b10111111 n
b10111111 o
b10111111 {
b10111111 |
b10111111 }
b11111111 l
b101011110 z
b100000 h
b10 g
b11111101 i
b11111101 e
b11111101 x
1D
b1111010 =
b1111010 M
b101000001 <
b101000001 L
b1111000000111101 8
b1111000000111101 J
b1110110010110101 7
b1110110010110101 I
b1010110110100 6
b1010110110100 H
b10110 @
b10110 O
b11111010100 ;
b11111010100 K
09
#345000
b101111 &
b101111 f
b101111 %
b101111 p
b101111 "
b101111 w
1!
b1111010 #
b1111010 v
b101000001 $
b101000001 u
19
#350000
b1001 F
b1010 G
0D
09
#355000
0!
19
#360000
09
#365000
b1010 #"
19
#370000
b1000001 r
b1000001 s
b1000001 t
b1000001 ~
b1000001 !"
b1000001 ""
b110101110 z
b1011011 h
b1110111 g
b10001000 i
b10001000 e
b10001000 x
b1011000 q
b100001 k
b100001 y
b10000100010 j
1D
b110011010 =
b110011010 M
b100001010 <
b100001010 L
b10000100010 8
b10000100010 J
b1110001110010011 7
b1110001110010011 I
b100010111010 6
b100010111010 H
b11011 @
b11011 O
b10001101 ;
b10001101 K
09
#375000
b1000001 &
b1000001 f
b1000001 %
b1000001 p
b1000001 "
b1000001 w
1!
b110011010 #
b110011010 v
b100001010 $
b100001010 u
19
#380000
b1010 F
b1011 G
0D
09
#385000
0!
19
#390000
09
#395000
b1011 #"
19
#400000
b111000 r
b10101 s
b10001 t
b111000 ~
b10101 !"
b10001 ""
b11100000 m
b1010110 n
b1000100 o
b11100000 {
b1010110 |
b1000100 }
b1001111 l
b1001111 z
b100111 h
b11110001 g
b1110 i
b1110 e
b1110 x
b1000000 q
b0 k
b0 y
b0 j
1D
b10100111 =
b10100111 M
b110101110 <
b110101110 L
b1111001100001100 8
b1111001100001100 J
b101111011001 7
b101111011001 I
b1110001111010010 6
b1110001111010010 H
b101 @
b101 O
b1111100011101011 ;
b1111100011101011 K
09
#405000
b111000 &
b111000 f
b10101 %
b10101 p
b10001 "
b10001 w
1!
b10100111 #
b10100111 v
b110101110 $
b110101110 u
19
#410000
b1011 F
b1100 G
0D
09
#415000
0!
19
#420000
09
#425000
b1100 #"
19
#430000
b101111 r
b101111 s
b101111 t
b101111 ~
b101111 !"
b101111 ""
b10111111 m
b10111111 n
b10111111 o
b10111111 {
b10111111 |
b10111111 }
b11111111 l
b111001110 z
b1001010 h
b10101010 g
b1010101 i
b1010101 e
b1010101 x
1D
b111001011 =
b111001011 M
b1000101001 <
b1000101001 L
b1111101000001010 8
b1111101000001010 J
b1111010011000010 7
b1111010011000010 I
b1111001010111000 6
b1111001010111000 H
b11101 @
b11101 O
b1111110101010111 ;
b1111110101010111 K
09
#435000
b101111 &
b101111 f
b101111 %
b101111 p
b101111 "
b101111 w
1!
b111001011 #
b111001011 v
b1000101001 $
b1000101001 u
19
#440000
b1100 F
b1101 G
0D
09
#445000
0!
19
#450000
09
#455000
b1101 #"
19
#460000
b10100010 r
b10100010 s
b10100010 t
b10100010 ~
b10100010 !"
b10100010 ""
b110111110 z
b1001001 h
b10101101 g
b1010010 i
b1010010 e
b1010010 x
b11011010 q
b11001111 k
b11001111 y
b1100111100011 j
1D
b10101100 =
b10101100 M
b1000110101 <
b1000110101 L
b1100111100011 8
b1100111100011 J
b1110000101100101 7
b1110000101100101 I
b1100101101101 6
b1100101101101 H
b11100 @
b11100 O
b1111110100100101 ;
b1111110100100101 K
09
#465000
b10100010 &
b10100010 f
b10100010 %
b10100010 p
b10100010 "
b10100010 w
1!
b10101100 #
b10101100 v
b1000110101 $
b1000110101 u
19
#470000
b1101 F
b1110 G
0D
09
#475000
0!
19
#480000
09
#485000
b1110 #"
19
#490000
b101111 r
b11000 s
b11000 t
b101111 ~
b11000 !"
b11000 ""
b10111101 m
b1100000 n
b1100000 o
b10111101 {
b1100000 |
b1100000 }
b111111 l
b111111 z
b1000001 h
b10111101 g
b1000010 i
b1000010 e
b1000010 x
b1000000 q
b0 k
b0 y
b0 j
1D
b100000111 =
b100000111 M
b110101101 <
b110101101 L
b1111000101001001 8
b1111000101001001 J
b110110001001 7
b110110001001 I
b1110000011100010 6
b1110000011100010 H
b100 @
b100 O
b1111110000101101 ;
b1111110000101101 K
09
#495000
b101111 &
b101111 f
b11000 %
b11000 p
b11000 "
b11000 w
1!
b100000111 #
b100000111 v
b110101101 $
b110101101 u
19
#500000
b1110 F
b1111 G
0D
09
#505000
0!
19
#510000
09
#515000
b1111 #"
19
#520000
b101000 r
b10011 s
b10110 t
b101000 ~
b10011 !"
b10110 ""
b10100010 m
b1001101 n
b1011011 o
b10100010 {
b1001101 |
b1011011 }
b0 l
b0 z
b1001110 h
b10100011 g
b1011100 i
b1011100 e
b1011100 x
1D
b110111 =
b110111 M
b110111011 <
b110111011 L
b1110100011110000 8
b1110100011110000 J
b1100101010010 7
b1100101010010 I
b1111110100011111 6
b1111110100011111 H
b0 @
b0 O
b1111110111000010 ;
b1111110111000010 K
b10 ?
b10 N
09
#525000
b11101011 &
b11101011 f
b11001110 %
b11001110 p
b10000111 "
b10000111 w
1!
b110111 #
b110111 v
b110111011 $
b110111011 u
19
#530000
b1111 F
b10000 G
0D
09
#535000
0!
19
#540000
09
#545000
b10000 #"
19
#550000
b101111 r
b101111 s
b101111 t
b101111 ~
b101111 !"
b101111 ""
b10111111 m
b10111111 n
b10111111 o
b10111111 {
b10111111 |
b10111111 }
b11111111 l
b110001110 z
b101111 h
b100000 g
b11011111 i
b11011111 e
b11011111 x
1D
b111011110 =
b111011110 M
b100010 <
b100010 L
b1111111111011011 8
b1111111111011011 J
b1110001010110010 7
b1110001010110010 I
b1101111001001 6
b1101111001001 H
b11001 @
b11001 O
b10111110111 ;
b10111110111 K
b0 ?
b0 N
09
#555000
1!
b111011110 #
b111011110 v
b100010 $
b100010 u
19
#560000
b10000 F
b10001 G
0D
09
#565000
0!
19
#570000
09
#575000
b10001 #"
19
#580000
b1000000 r
b1000000 s
b1000000 t
b1000000 ~
b1000000 !"
b1000000 ""
b101111110 z
b1001111 h
b1011111 g
b10100000 i
b10100000 e
b10100000 x
b1010111 q
b11111 k
b11111 y
b1111110100 j
1D
b10011001 =
b10011001 M
b1001010100 <
b1001010100 L
b1111110100 8
b1111110100 J
b1111100100010010 7
b1111100100010010 I
b1001010011101 6
b1001010011101 H
b11000 @
b11000 O
b1000000010 ;
b1000000010 K
09
